multi_convention_namer/__init__.py
multi_convention_namer/py.typed
multi_convention_namer/_jsii/__init__.py
multi_convention_namer/_jsii/multi-convention-namer@0.0.0.jsii.tgz
multi_convention_namer-0.0.0.dist-info/LICENSE
multi_convention_namer-0.0.0.dist-info/METADATA
multi_convention_namer-0.0.0.dist-info/WHEEL
multi_convention_namer-0.0.0.dist-info/top_level.txt
multi_convention_namer-0.0.0.dist-info/RECORD
