Metadata-Version: 2.1
Name: multi-convention-namer
Version: 0.0.0
Summary: A string manipulation library to facilitate dealing with multiple naming conventions
Home-page: https://github.com/myhelix/multi-convention-namer
Author: Andrew Hammond<andrew.george.hammond@gmail.com>
License: Apache-2.0
Project-URL: Source, https://github.com/myhelix/multi-convention-namer
Platform: UNKNOWN
Classifier: Intended Audience :: Developers
Classifier: Operating System :: OS Independent
Classifier: Programming Language :: JavaScript
Classifier: Programming Language :: Python :: 3 :: Only
Classifier: Programming Language :: Python :: 3.6
Classifier: Programming Language :: Python :: 3.7
Classifier: Programming Language :: Python :: 3.8
Classifier: Programming Language :: Python :: 3.9
Classifier: Typing :: Typed
Classifier: Development Status :: 5 - Production/Stable
Classifier: License :: OSI Approved
Requires-Python: >=3.6
License-File: LICENSE
Requires-Dist: jsii (<2.0.0,>=1.34.0)
Requires-Dist: publication (>=0.0.3)
